<?xml version="1.0"?>
<tryton>
    <data>
        
        <record model="ir.ui.view" id="employee_mileage_form">
            <field name="name">employee_mileage_form</field>
            <field name="model">employee_mileage</field>
            <field name="type">form</field>
        </record>

        <record model="ir.ui.view" id="employee_mileage_list">
            <field name="name">employee_mileage_list</field>
            <field name="model">employee_mileage</field>
            <field name="type">tree</field>
        </record>

       <record model="ir.action.act_window" id="act_employee_mileage">
            <field name="name">Employee mileage</field>   <!-- Nombre que verá el usuario en pantalla -->
            <field name="res_model">employee_mileage</field>
        </record>

        <record model="ir.action.act_window.view" id="act_employee_mileage_form">
            <field name="sequence" eval="10"/>
            <field name="view" ref="employee_mileage_form"/>
            <field name="act_window" ref="act_employee_mileage" />
        </record>

        <record model="ir.action.act_window.view" id="act_employee_mileage_list">
            <field name="sequence" eval="20"/>
            <field name="view" ref="employee_mileage_list"/>
            <field name="act_window" ref="act_employee_mileage" />
        </record>

        <menuitem id="menu_mileage" parent="company.menu_company" sequence="1" icon="tryton-list" action="act_employee_mileage" />
    
    </data>
</tryton>